oda_reader/__init__.py
oda_reader/_cache/README.md
oda_reader/_cache/__init__.py
oda_reader/_cache/config.py
oda_reader/_cache/dataframe.py
oda_reader/_cache/legacy.py
oda_reader/_cache/manager.py
oda_reader/aiddata.py
oda_reader/common.py
oda_reader/crs.py
oda_reader/dac1.py
oda_reader/dac2a.py
oda_reader/download/__init__.py
oda_reader/download/download_tools.py
oda_reader/download/query_builder.py
oda_reader/multisystem.py
oda_reader/schemas/__init__.py
oda_reader/schemas/crs_translation.py
oda_reader/schemas/dac1_translation.py
oda_reader/schemas/dac2_translation.py
oda_reader/schemas/mappings/aidData_schema.json
oda_reader/schemas/mappings/area_code_corrections.json
oda_reader/schemas/mappings/code_prices_corrections.json
oda_reader/schemas/mappings/crs_dotstat.json
oda_reader/schemas/mappings/dac1_codes_area.json
oda_reader/schemas/mappings/dac1_codes_flow_types.json
oda_reader/schemas/mappings/dac1_codes_prices.json
oda_reader/schemas/mappings/dac1_dotstat.json
oda_reader/schemas/mappings/dac2_codes_area.json
oda_reader/schemas/mappings/dac2a_dotstat.json
oda_reader/schemas/mappings/multisystem_dotstat.json
oda_reader/schemas/multisystem_translation.py
oda_reader/schemas/schema_tools.py
oda_reader/schemas/xml_tools.py
oda_reader/tools.py
oda_reader-1.4.2.dist-info/WHEEL
oda_reader-1.4.2.dist-info/METADATA
oda_reader-1.4.2.dist-info/RECORD
