Metadata-Version: 2.4
Name: oda-reader
Version: 1.4.2
Summary: A simple package to import ODA data from the OECD's API and AidData's database
Author: Jorge Rivera
Author-email: Jorge Rivera <jorge.rivera@one.org>
License-Expression: MIT
Classifier: Development Status :: 5 - Production/Stable
Classifier: Intended Audience :: Developers
Classifier: Intended Audience :: Science/Research
Classifier: License :: OSI Approved :: MIT License
Classifier: Operating System :: OS Independent
Classifier: Programming Language :: Python :: 3
Classifier: Programming Language :: Python :: 3.10
Classifier: Programming Language :: Python :: 3.11
Classifier: Programming Language :: Python :: 3.12
Classifier: Programming Language :: Python :: 3.13
Classifier: Programming Language :: Python :: 3 :: Only
Classifier: Topic :: Scientific/Engineering
Classifier: Topic :: Software Development :: Libraries :: Python Modules
Requires-Dist: filelock>=3.18.0
Requires-Dist: joblib>=1.4
Requires-Dist: openpyxl>=3.1.0
Requires-Dist: pandas>=2.2.0
Requires-Dist: platformdirs>=4.5.0
Requires-Dist: pyarrow>=14.0.0
Requires-Dist: requests>=2.32
Requires-Dist: requests-cache>=1.2.0
Requires-Python: >=3.10
